[{"0":"25","id":"25","1":"1","Galeria":"1","2":"sdcsd","Nombre":"sdcsd","3":"sdcsdc","Descripcion":"sdcsdc","4":"222","Costo":"222","5":"1479883892.jpg","UrlFile":"1479883892.jpg"},{"0":"26","id":"26","1":"2","Galeria":"2","2":"hombrees","Nombre":"hombrees","3":"hombres","Descripcion":"hombres","4":"9999","Costo":"9999","5":"1479884313.jpg","UrlFile":"1479884313.jpg"},{"0":"24","id":"24","1":"1","Galeria":"1","2":"NIKE METCON 2 AMP","Nombre":"NIKE METCON 2 AMP","3":"Entrenamiento","Descripcion":"Entrenamiento","4":"1538","Costo":"1538","5":"1479873949.jpg","UrlFile":"1479873949.jpg"},{"0":"23","id":"23","1":"1","Galeria":"1","2":"NIKE METCON 2 ULTD","Nombre":"NIKE METCON 2 ULTD","3":"CALZADO DE ENTRENAMI","Descripcion":"CALZADO DE ENTRENAMI","4":"2199","Costo":"2199","5":"1479873912.jpg","UrlFile":"1479873912.jpg"},{"0":"22","id":"22","1":"1","Galeria":"1","2":"NIKE METCON 2 AMP","Nombre":"NIKE METCON 2 AMP","3":"CALZADO DE ENTRENAMI","Descripcion":"CALZADO DE ENTRENAMI","4":"1500","Costo":"1500","5":"1479873893.jpg","UrlFile":"1479873893.jpg"},{"0":"21","id":"21","1":"1","Galeria":"1","2":"Nike Metcon 2","Nombre":"Nike Metcon 2","3":"CALZADO DE ENTRENAMI","Descripcion":"CALZADO DE ENTRENAMI","4":"2199","Costo":"2199","5":"1479873831.jpg","UrlFile":"1479873831.jpg"}]